atom/__init__.py
atom/_show_versions.py
atom/api.py
atom/atom.py
atom/basemodel.py
atom/baserunner.py
atom/basetracker.py
atom/basetrainer.py
atom/basetransformer.py
atom/data/__init__.py
atom/data/branch.py
atom/data/branchmanager.py
atom/data/dataengines.py
atom/data_cleaning.py
atom/feature_engineering.py
atom/integrations.py
atom/models/__init__.py
atom/models/classreg.py
atom/models/custom.py
atom/models/ensembles.py
atom/models/ts.py
atom/nlp.py
atom/pipeline.py
atom/plots/__init__.py
atom/plots/basefigure.py
atom/plots/baseplot.py
atom/plots/dataplot.py
atom/plots/hyperparametertuningplot.py
atom/plots/predictionplot.py
atom/plots/shapplot.py
atom/training.py
atom/utils/__init__.py
atom/utils/constants.py
atom/utils/patches.py
atom/utils/types.py
atom/utils/utils.py
atom_ml-6.1.0.dist-info/METADATA
atom_ml-6.1.0.dist-info/WHEEL
atom_ml-6.1.0.dist-info/licenses/LICENSE
atom_ml-6.1.0.dist-info/RECORD
