Metadata-Version: 2.1
Name: atom-ml
Version: 6.1.0
Summary: A Python package for fast exploration of machine learning pipelines
Keywords: Python package,Machine Learning,Modeling,Data Pipeline
Author-Email: Mavs <m.524687@gmail.com>
License: MIT License
Classifier: Programming Language :: Python :: 3.10
Classifier: Programming Language :: Python :: 3.11
Classifier: Programming Language :: Python :: 3.12
Classifier: Topic :: Scientific/Engineering :: Artificial Intelligence
Classifier: License :: OSI Approved :: MIT License
Classifier: Operating System :: OS Independent
Project-URL: Documentation, https://tvdboom.github.io/ATOM/
Project-URL: Issues, https://github.com/tvdboom/ATOM/issues
Project-URL: Repository, https://github.com/tvdboom/ATOM
Project-URL: Slack, https://join.slack.com/t/atom-alm7229/shared_invite/zt-upd8uc0z-LL63MzBWxFf5tVWOGCBY5g
Requires-Python: <3.13,>=3.10
Requires-Dist: beartype>=0.18.5
Requires-Dist: category-encoders>=2.6.3
Requires-Dist: dill>=0.3.6
Requires-Dist: featuretools>=1.28.0
Requires-Dist: gplearn>=0.4.2
Requires-Dist: imbalanced-learn>=0.12.3
Requires-Dist: ipython>=8.9.0
Requires-Dist: ipywidgets>=8.1.1
Requires-Dist: joblib>=1.3.1
Requires-Dist: matplotlib>=3.7.2
Requires-Dist: mlflow>=2.10.2
Requires-Dist: nltk>=3.8.1
Requires-Dist: numpy>=1.23.0
Requires-Dist: optuna>=3.6.0
Requires-Dist: pandas>=2.2.2
Requires-Dist: plotly>=5.18.0
Requires-Dist: scikit-learn>=1.5.0
Requires-Dist: scipy>=1.10.1
Requires-Dist: shap>=0.43.0
Requires-Dist: sktime[forecasting]>=0.30.0
Requires-Dist: statsmodels>=0.14.1
Requires-Dist: zoofs>=0.1.25
Requires-Dist: botorch>=0.8.5; python_version < "3.12" and extra == "full"
Requires-Dist: catboost>=1.2; extra == "full"
Requires-Dist: dagshub>=0.3.8; extra == "full"
Requires-Dist: dask[dataframe,distributed]>=2024.2.0; extra == "full"
Requires-Dist: explainerdashboard>=0.4.3; extra == "full"
Requires-Dist: gradio>=3.44.4; extra == "full"
Requires-Dist: lightgbm>=4.1.0; extra == "full"
Requires-Dist: modin[ray]>=0.25.0; python_version < "3.12" and extra == "full"
Requires-Dist: optuna-integration>=3.6.0; extra == "full"
Requires-Dist: polars>=0.20.7; extra == "full"
Requires-Dist: pyarrow>=15.0.0; extra == "full"
Requires-Dist: pyspark>=3.5.0; extra == "full"
Requires-Dist: ray[serve]>=2.9.1; python_version < "3.12" and extra == "full"
Requires-Dist: requests>=2.31.0; extra == "full"
Requires-Dist: scikit-learn-intelex>=2023.2.1; platform_system != "Darwin" and (platform_machine == "x86_64" or platform_machine == "AMD64") and extra == "full"
Requires-Dist: schemdraw>=0.16; extra == "full"
Requires-Dist: statsforecast>=1.7.3; extra == "full"
Requires-Dist: supersmoother>=0.4; extra == "full"
Requires-Dist: sweetviz>=2.3.1; extra == "full"
Requires-Dist: wordcloud>=1.9.2; extra == "full"
Requires-Dist: xgboost>=2.0.0; extra == "full"
Provides-Extra: full
